Metadata-Version: 2.1
Name: dynascii
Version: 1.4.0.1
Summary: Dynascii is a light-weighted utility or application to casting things to a stream. It is implemented in Python and aimed to deploy quickly and easily on a server with a proper environment.
Home-page: https://github.com/Tarcadia/Dynascii
Author: Tarcadia
Author-email: dont@email.me
License: GNU GENERAL PUBLIC LICENSE VERSION 3
Project-URL: Bug Reports, https://github.com/Tarcadia/Dynascii/issues
Project-URL: Source, https://github.com/Tarcadia/Dynascii
Keywords: Dynascii,ASCII,ASCII Art,TELNET,Tarcadia
Classifier: Development Status :: 5 - Production/Stable
Classifier: Environment :: Console
Classifier: Intended Audience :: Developers
Classifier: License :: OSI Approved :: GNU General Public License v3 (GPLv3)
Classifier: Programming Language :: Python :: 3.8
Requires-Python: >=3.7, <4
License-File: LICENSE
